MANIFEST.in
README.rst
setup.py
icet/__init__.py
icet/core/__init__.py
icet/core/cluster.py
icet/core/cluster_counts.py
icet/core/cluster_expansion.py
icet/core/cluster_space.py
icet/core/lattice_site.py
icet/core/local_orbit_list_generator.py
icet/core/many_body_neighbor_list.py
icet/core/matrix_of_equivalent_positions.py
icet/core/neighbor_list.py
icet/core/orbit.py
icet/core/orbit_list.py
icet/core/structure.py
icet/core/structure_container.py
icet/core/sublattices.py
icet/fitting/__init__.py
icet/fitting/base_optimizer.py
icet/fitting/cross_validation.py
icet/fitting/ensemble_optimizer.py
icet/fitting/fit_methods.py
icet/fitting/oi.py
icet/fitting/optimizer.py
icet/fitting/split_bregman.py
icet/fitting/tools.py
icet/input_output/__init__.py
icet/input_output/logging_tools.py
icet/tools/__init__.py
icet/tools/constraints.py
icet/tools/convex_hull.py
icet/tools/geometry.py
icet/tools/ground_state_finder.py
icet/tools/structure_enumeration.py
icet/tools/structure_generation.py
icet/tools/structure_mapping.py
icet/tools/variable_transformation.py
icet/tools/structure_enumeration_support/__init__.py
icet/tools/structure_enumeration_support/labeling_generation.py
icet/tools/structure_enumeration_support/normal_form_matrices.py
mchammer/__init__.py
mchammer/configuration_manager.py
mchammer/data_analysis.py
mchammer/calculators/__init__.py
mchammer/calculators/base_calculator.py
mchammer/calculators/cluster_expansion_calculator.py
mchammer/calculators/target_vector_calculator.py
mchammer/data_containers/__init__.py
mchammer/data_containers/base_data_container.py
mchammer/data_containers/data_container.py
mchammer/data_containers/wang_landau_data_container.py
mchammer/ensembles/__init__.py
mchammer/ensembles/base_ensemble.py
mchammer/ensembles/canonical_annealing.py
mchammer/ensembles/canonical_ensemble.py
mchammer/ensembles/hybrid_ensemble.py
mchammer/ensembles/semi_grand_canonical_ensemble.py
mchammer/ensembles/sgc_annealing.py
serhiisavruk_kxQ2GLDZtw.egg-info/PKG-INFO
serhiisavruk_kxQ2GLDZtw.egg-info/SOURCES.txt
serhiisavruk_kxQ2GLDZtw.egg-info/dependency_links.txt
serhiisavruk_kxQ2GLDZtw.egg-info/not-zip-safe
serhiisavruk_kxQ2GLDZtw.egg-info/requires.txt
serhiisavruk_kxQ2GLDZtw.egg-info/top_level.txt
