Metadata-Version: 1.1
Name: serhiisavruk-kxQ2GLDZtw
Version: 1.3.11
Summary: A Pythonic approach to cluster expansions
Home-page: http://icet.materialsmodeling.org/
Author: icet developer group
Author-email: icet@materialsmodeling.org
License: Mozilla Public License 2.0 (MPL 2.0)
Platform: UNKNOWN
Classifier: Development Status :: 5 - Production/Stable
Classifier: Operating System :: OS Independent
Classifier: Programming Language :: Python :: 3 :: Only
Classifier: Programming Language :: Python :: 3
Classifier: Programming Language :: Python :: 3.6
Classifier: Programming Language :: Python :: 3.7
Classifier: Intended Audience :: Science/Research
Classifier: License :: OSI Approved :: Mozilla Public License 2.0 (MPL 2.0)
Classifier: Topic :: Scientific/Engineering :: Physics
